[
  {
    "rank": 2,
    "title": "Mini Mic Pro Wireless Microphone for iPhone, iPad, Android, Lavalier Microphone for Video Recording - 2 Pack iPhone Mic Crystal Clear Recording with USB-C for Podcast, ASMR",
    "link": "https://www.amazon.com/Mini-Mic-Pro-Professional-Microphone/dp/B0CMJTSVRW/ref=zg_bs_g_musical-instruments_d_sccl_1/131-9998848-2129151?psc=1?tag=101e2e-20",
    "image": "https://images-na.ssl-images-amazon.com/images/I/711s6fypzWL._AC_UL300_SR300,200_.jpg",
    "price": "$24.32",
    "rating": "4.3"
  },
  {
    "rank": 5,
    "title": "Ernie Ball Regular Slinky Nickel Wound Electric Guitar Strings, 10-46 Gauge (P02221)",
    "link": "https://www.amazon.com/Ernie-Ball-Regular-Slinky-Nickel/dp/B0002M6CVC/ref=zg_bs_g_musical-instruments_d_sccl_2/131-9998848-2129151?psc=1?tag=101e2e-20",
    "image": "https://images-na.ssl-images-amazon.com/images/I/81wMsbKBB9L._AC_UL300_SR300,200_.jpg",
    "price": "$6.99",
    "rating": "4.8"
  },
  {
    "rank": 8,
    "title": "Amazon Basics Adjustable Folding Guitar Stand, A-shape, Fully Assembled - For School Music Program, Concerts & Multiple Users, Black",
    "link": "https://www.amazon.com/AmazonBasics-Folding-Acoustic-Electric-Guitars/dp/B018FCZKR2/ref=zg_bs_g_musical-instruments_d_sccl_3/131-9998848-2129151?psc=1?tag=101e2e-20",
    "image": "https://images-na.ssl-images-amazon.com/images/I/61cliBBijoL._AC_UL300_SR300,200_.jpg",
    "price": "$14.99",
    "rating": "4.8"
  },
  {
    "rank": 11,
    "title": "D'Addario Acoustic Guitar Strings - 80/20 Bronze - For 6 String Guitars - Deep, Bright, Projecting Tone - EJ11 - Light, 12-53",
    "link": "https://www.amazon.com/DAddario-EJ11-Bronze-Acoustic-Strings/dp/B000EEL6GY/ref=zg_bs_g_musical-instruments_d_sccl_4/131-9998848-2129151?psc=1?tag=101e2e-20",
    "image": "https://images-na.ssl-images-amazon.com/images/I/81HJEjIzQUL._AC_UL300_SR300,200_.jpg",
    "price": "$6.89",
    "rating": "4.7"
  },
  {
    "rank": 14,
    "title": "DJI Mic Mini (2 TX + 1 RX + Charging Case), Wireless Microphone for iPhone/Camera/Android, Ultralight, Detail-Rich Audio, 48h Use, Noise Cancelling, Automatic Limiting, Vlog, Streaming",
    "link": "https://www.amazon.com/DJI-Microphone-Ultralight-Detail-Rich-Cancelling/dp/B0DDL8WGH5/ref=zg_bs_g_musical-instruments_d_sccl_5/131-9998848-2129151?psc=1?tag=101e2e-20",
    "image": "https://images-na.ssl-images-amazon.com/images/I/6132m-fHnjL._AC_UL300_SR300,200_.jpg",
    "price": "$166.68",
    "rating": "4.7"
  },
  {
    "rank": 17,
    "title": "Amazon Basics XLR Male to Female Microphone Cable for Speaker or PA System, All Copper Conductors, 6MM PVC Jacket, 6 Foot, Black",
    "link": "https://www.amazon.com/Amazon-Basics-Microphone-Speaker-Conductors/dp/B01JNLTTKS/ref=zg_bs_g_musical-instruments_d_sccl_6/131-9998848-2129151?psc=1?tag=101e2e-20",
    "image": "https://images-na.ssl-images-amazon.com/images/I/71MU3AzBnCL._AC_UL300_SR300,200_.jpg",
    "price": "$7.64",
    "rating": "4.7"
  },
  {
    "rank": 20,
    "title": "OneOdio Wired Over Ear Headphones Hi-Res Studio Monitor & Mixing DJ Stereo Headsets with 50mm Drivers and 1/4 to 3.5mm Jack for AMP Computer Recording Podcast Keyboard Guitar Laptop - Black",
    "link": "https://www.amazon.com/OneOdio-PRO1030-DJ-Headphone-Black/dp/B01N6ZJH96/ref=zg_bs_g_musical-instruments_d_sccl_7/131-9998848-2129151?psc=1?tag=101e2e-20",
    "image": "https://images-na.ssl-images-amazon.com/images/I/71MzTsi7UjL._AC_UL300_SR300,200_.jpg",
    "price": "$35.99",
    "rating": "4.4"
  },
  {
    "rank": 23,
    "title": "Bubble Machine, Automatic 18000+ Per Minute Big Bubbles Blower Maker for Kids Toddlers with 2 Speeds,6 Wands,Operated by Plugin or Batteries for Outdoor/Indoor Birthday Parties,Wedding (Black)",
    "link": "https://www.amazon.com/Machine-Automatic-Operated-Batteries-Birthday/dp/B0CX4C1HTL/ref=zg_bs_g_musical-instruments_d_sccl_8/131-9998848-2129151?psc=1?tag=101e2e-20",
    "image": "https://images-na.ssl-images-amazon.com/images/I/710WKATXl6L._AC_UL300_SR300,200_.jpg",
    "price": "$23.99",
    "rating": "4.3"
  },
  {
    "rank": 26,
    "title": "Elixir Strings, Acoustic Guitar Strings, 80/20 Bronze with NANOWEB Coating, Longest-Lasting Bright and Focused Tone with Comfortable Feel, 6 String Set, Light 12-53",
    "link": "https://www.amazon.com/Elixir-Strings-Acoustic-NANOWEB-012-053/dp/B0002E1O2C/ref=zg_bs_g_musical-instruments_d_sccl_9/131-9998848-2129151?psc=1?tag=101e2e-20",
    "image": "https://images-na.ssl-images-amazon.com/images/I/91uQmrejH9L._AC_UL300_SR300,200_.jpg",
    "price": "$16.98",
    "rating": "4.8"
  },
  {
    "rank": 29,
    "title": "MAYBESTA 2 in 1 Wireless Mini Microphone for iPhone, iPad, Android Phone - Bluetooth Lavalier Lapel Mic for Video Recording - Clip on USB C Microphones for YouTube Tiktok Podcast Vlogging",
    "link": "https://www.amazon.com/Professional-Wireless-Lavalier-Microphone-iPhone/dp/B09P3T1X8Q/ref=zg_bs_g_musical-instruments_d_sccl_10/131-9998848-2129151?psc=1?tag=101e2e-20",
    "image": "https://images-na.ssl-images-amazon.com/images/I/712VjEn-btL._AC_UL300_SR300,200_.jpg",
    "price": "$22.99",
    "rating": "4.2"
  },
  {
    "rank": 32,
    "title": "PQRQP 3 in 1 Microphone for iPhone/Android/Camera, Wireless Lavalier Microphone, 328ft Transmission, 18H Battery Life, Mini Microphone for Record Interview, Vlogs, YouTube, Tiktok",
    "link": "https://www.amazon.com/PQRQP-Dual-Clip-Microphone-WVK/dp/B0CY7P3WVK/ref=zg_bs_g_musical-instruments_d_sccl_11/131-9998848-2129151?psc=1?tag=101e2e-20",
    "image": "https://images-na.ssl-images-amazon.com/images/I/61uIE-QzJEL._AC_UL300_SR300,200_.jpg",
    "price": "$39.98",
    "rating": "4.4"
  },
  {
    "rank": 35,
    "title": "FIFINE USB/XLR Dynamic Microphone for Podcast Recording, PC Computer Gaming Streaming Mic with RGB Light, Mute Button, Headphones Jack, Desktop Stand, Vocal Mic for Singing YouTube-AmpliGame AM8",
    "link": "https://www.amazon.com/FIFINE-Microphone-Headphones-YouTube-AmpliGame-AM8/dp/B0BMFQP2ZZ/ref=zg_bs_g_musical-instruments_d_sccl_12/131-9998848-2129151?psc=1?tag=101e2e-20",
    "image": "https://images-na.ssl-images-amazon.com/images/I/71k6li+9vFL._AC_UL300_SR300,200_.jpg",
    "price": "$43.64",
    "rating": "4.5"
  },
  {
    "rank": 38,
    "title": "Focusrite Scarlett Solo 3rd Gen USB Audio Interface for Guitarists, Vocalists, Podcasters or Producers to record and playback studio quality sound",
    "link": "https://www.amazon.com/Focusrite-Scarlett-Audio-Interface-Tools/dp/B07QR6Z1JB/ref=zg_bs_g_musical-instruments_d_sccl_13/131-9998848-2129151?psc=1?tag=101e2e-20",
    "image": "https://images-na.ssl-images-amazon.com/images/I/613veRuWtmL._AC_UL300_SR300,200_.jpg",
    "price": "$109.99",
    "rating": "4.6"
  },
  {
    "rank": 41,
    "title": "New bee Guitar Cable 10ft Electric Instrument Bass AMP Cord for Electric Mandolin, Pro Audio (Right Angle to Straight, Black)",
    "link": "https://www.amazon.com/New-bee-Electric-Instrument-Mandolin/dp/B07TT2D4RR/ref=zg_bs_g_musical-instruments_d_sccl_14/131-9998848-2129151?psc=1?tag=101e2e-20",
    "image": "https://images-na.ssl-images-amazon.com/images/I/71ivgeiqfcL._AC_UL300_SR300,200_.jpg",
    "price": "$7.99",
    "rating": "4.7"
  },
  {
    "rank": 44,
    "title": "D'Addario Guitar Strings - Phosphor Bronze Acoustic Guitar Strings - EJ16-3D - Rich, Full Tonal Spectrum - For 6 String Guitars - 12-53 Light, 3-Pack",
    "link": "https://www.amazon.com/DAddario-EJ16-3D-Phosphor-Acoustic-Strings/dp/B000OR2RNM/ref=zg_bs_g_musical-instruments_d_sccl_15/131-9998848-2129151?psc=1?tag=101e2e-20",
    "image": "https://images-na.ssl-images-amazon.com/images/I/71PmPjL1q5L._AC_UL300_SR300,200_.jpg",
    "price": "$17.99",
    "rating": "4.7"
  },
  {
    "rank": 47,
    "title": "FIFINE XLR/USB Gaming Microphone Set, Dynamic PC Mic for Streaming Podcasting, Computer RGB Mic Kit with Boom Arm Stand, Mute Button, Headphones Jack, for Recording Vocal Voice-Over-AmpliGame AM8T",
    "link": "https://www.amazon.com/FIFINE-Microphone-Podcasting-Voice-Over-AmpliGame-AM8T/dp/B0C74GYW3J/ref=zg_bs_g_musical-instruments_d_sccl_16/131-9998848-2129151?psc=1?tag=101e2e-20",
    "image": "https://images-na.ssl-images-amazon.com/images/I/61-0YoCB2LL._AC_UL300_SR300,200_.jpg",
    "price": "$51.99",
    "rating": "4.6"
  },
  {
    "rank": 50,
    "title": "D'Addario Guitar Strings - XL Nickel Electric Guitar Strings - EXL110-3D - Perfect Intonation, Consistent Feel, Reliable Durability - For 6 String Guitars - 10-46 Regular Light, 3-Pack",
    "link": "https://www.amazon.com/DAddario-EXL110-3D-Electric-Strings-Regular/dp/B000EEJ91I/ref=zg_bs_g_musical-instruments_d_sccl_17/131-9998848-2129151?psc=1?tag=101e2e-20",
    "image": "https://images-na.ssl-images-amazon.com/images/I/81GF5wh1cVL._AC_UL300_SR300,200_.jpg",
    "price": "$17.99",
    "rating": "4.8"
  },
  {
    "rank": 53,
    "title": "USB C Mini Wireless Lavalier Microphone for iPhone 15 16, iOS and Android Devices - Noise Reduction Lapel Mic for Recording, Clip on Mic, Omni Lav Mic for Video Recording, Tiktok, Youtube, Vlog",
    "link": "https://www.amazon.com/Wireless-Lavalier-Microphone-Android-Devices/dp/B0CL4XJ5GJ/ref=zg_bs_g_musical-instruments_d_sccl_18/131-9998848-2129151?psc=1?tag=101e2e-20",
    "image": "https://images-na.ssl-images-amazon.com/images/I/71UcFNBOheL._AC_UL300_SR300,200_.jpg",
    "price": "$11.38",
    "rating": "4.3"
  },
  {
    "rank": 56,
    "title": "Fender FCT-2 Professional Clip-On Tuner",
    "link": "https://www.amazon.com/Fender-FCT-2-Professional-Clip-On-Tuner/dp/B074KGZ9Z7/ref=zg_bs_g_musical-instruments_d_sccl_19/131-9998848-2129151?psc=1?tag=101e2e-20",
    "image": "https://images-na.ssl-images-amazon.com/images/I/81lgghn51OL._AC_UL300_SR300,200_.jpg",
    "price": "$21.99",
    "rating": "4.6"
  },
  {
    "rank": 59,
    "title": "WINGO Guitar Capo for Acoustic and Electric Guitars - Rosewood Color with 5 Picks",
    "link": "https://www.amazon.com/WINGO-Acoustic-Electric-Ukulele-Rosewood/dp/B073LSS9TJ/ref=zg_bs_g_musical-instruments_d_sccl_20/131-9998848-2129151?psc=1?tag=101e2e-20",
    "image": "https://images-na.ssl-images-amazon.com/images/I/71+4zd1hMdL._AC_UL300_SR300,200_.jpg",
    "price": "$8.98",
    "rating": "4.8"
  },
  {
    "rank": 62,
    "title": "Elixir Strings, Acoustic Guitar Strings, Phosphor Bronze with NANOWEB Coating, Longest-Lasting Rich and Full Tone with Comfortable Feel, 6 String Set, Light 12-53",
    "link": "https://www.amazon.com/Elixir-Strings-Phosphor-Acoustic-012-053/dp/B000A6ASSS/ref=zg_bs_g_musical-instruments_d_sccl_21/131-9998848-2129151?psc=1?tag=101e2e-20",
    "image": "https://images-na.ssl-images-amazon.com/images/I/91M12vhP7GL._AC_UL300_SR300,200_.jpg",
    "price": "$19.99",
    "rating": "4.8"
  },
  {
    "rank": 65,
    "title": "BONAOK Wireless Bluetooth Karaoke Microphone,3-in-1 Portable Handheld Karaoke Mic Speaker Machine Home Party Birthday for All Smartphones PC(Q37 Rose Gold)",
    "link": "https://www.amazon.com/BONAOK-Bluetooth-Microphone-Christmas-Smartphone/dp/B071SGMQ7V/ref=zg_bs_g_musical-instruments_d_sccl_22/131-9998848-2129151?psc=1?tag=101e2e-20",
    "image": "https://images-na.ssl-images-amazon.com/images/I/61C7uYbrI9L._AC_UL300_SR300,200_.jpg",
    "price": "$19.99",
    "rating": "4.4"
  },
  {
    "rank": 68,
    "title": "Hollyland Lark M2 Wireless Lavalier Microphone for iPhone/Android/Camera/PC/Laptop with Lightning/USB-C/Plug, 48KHz 24Bit, 1000ft Range, Noise Cancellation, 30H Battery for Video Recording, Streaming",
    "link": "https://www.amazon.com/Hollyland-Microphone-Lightning-Cancellation-Recording/dp/B0CP7QXWPN/ref=zg_bs_g_musical-instruments_d_sccl_23/131-9998848-2129151?psc=1?tag=101e2e-20",
    "image": "https://images-na.ssl-images-amazon.com/images/I/81ZyDI+YhfL._AC_UL300_SR300,200_.jpg",
    "price": "$119.00",
    "rating": "4.7"
  },
  {
    "rank": 71,
    "title": "Guitar Wall Mount 2 Pack, Black Walnut Wood Guitar Hanger, U-Shaped Guitar Wall Hanger Mount, Guitar Holder Hook Stand Wall for Acoustic, Electric Guitar, Banjo, Bass, for Guitar Player Men Boy",
    "link": "https://www.amazon.com/Guitar-U-Shaped-Acoustic-Electric-Mandolin/dp/B09WVZMKWG/ref=zg_bs_g_musical-instruments_d_sccl_24/131-9998848-2129151?psc=1?tag=101e2e-20",
    "image": "https://images-na.ssl-images-amazon.com/images/I/617bRPZXSbL._AC_UL300_SR300,200_.jpg",
    "price": "$16.99",
    "rating": "4.7"
  },
  {
    "rank": 74,
    "title": "Mini Karaoke Machine, Portable Bluetooth Karaoke Speaker with 2 Wireless Microphones and Party Lights for Kids and Adults, Birthday Gifts for Girls Boys Family Home Party",
    "link": "https://www.amazon.com/Portable-Bluetooth-Wireless-Microphones-Birthday/dp/B0CNX6MMK3/ref=zg_bs_g_musical-instruments_d_sccl_25/131-9998848-2129151?psc=1?tag=101e2e-20",
    "image": "https://images-na.ssl-images-amazon.com/images/I/8193Fr0kmwL._AC_UL300_SR300,200_.jpg",
    "price": "$21.99",
    "rating": "4.6"
  },
  {
    "rank": 77,
    "title": "Blue Yeti USB Mic for Recording and Streaming on PC and Mac with Blue VOCE Effects, 4 Pickup Patterns, Headphone Output and Volume Control, Mic Gain Control, Adjustable Stand, Plug & Play \u2013 Blackout",
    "link": "https://www.amazon.com/Recording-Streaming-Patterns-Headphone-Adjustable/dp/B00N1YPXW2/ref=zg_bs_g_musical-instruments_d_sccl_26/131-9998848-2129151?psc=1?tag=101e2e-20",
    "image": "https://images-na.ssl-images-amazon.com/images/I/61KTMvS5JBL._AC_UL300_SR300,200_.jpg",
    "price": "$71.02",
    "rating": "4.6"
  },
  {
    "rank": 80,
    "title": "Amazon Basics Height Adjustable Foldable Guitar Stand with Secure Support for Acoustic, Electric, Bass and Banjos, Sturdy, Black",
    "link": "https://www.amazon.com/Amazon-Basics-Adjustable-Acoustic-Electric/dp/B0BG7JWCHV/ref=zg_bs_g_musical-instruments_d_sccl_27/131-9998848-2129151?psc=1?tag=101e2e-20",
    "image": "https://images-na.ssl-images-amazon.com/images/I/41L1PdibCqL._AC_UL300_SR300,200_.jpg",
    "price": "$11.66",
    "rating": "4.5"
  },
  {
    "rank": 83,
    "title": "DECOSIS Projector Stand Tripod from 23\" to 46\", Laptop Tripod Stand Height Adjustable with Gooseneck Phone Holder, Laptop Floor Stand for Office, Home, Stage, Studio, DJ Racks Holder Mount",
    "link": "https://www.amazon.com/DECOSIS-Water-Balloons-Outdoor-Activities/dp/B09T6KYSCX/ref=zg_bs_g_musical-instruments_d_sccl_28/131-9998848-2129151?psc=1?tag=101e2e-20",
    "image": "https://images-na.ssl-images-amazon.com/images/I/61jdo1arLML._AC_UL300_SR300,200_.jpg",
    "price": "$31.72",
    "rating": "4.4"
  },
  {
    "rank": 86,
    "title": "Fender Premium Picks Sampler - 12 Pack Includes Thin, Medium & Heavy Gauges (Austin Bazaar Exclusive)",
    "link": "https://www.amazon.com/Fender-Premium-Picks-Sampler-Exclusive/dp/B07ZRYKNGS/ref=zg_bs_g_musical-instruments_d_sccl_29/131-9998848-2129151?psc=1?tag=101e2e-20",
    "image": "https://images-na.ssl-images-amazon.com/images/I/716q0kHyA-L._AC_UL300_SR300,200_.jpg",
    "price": "$13.99",
    "rating": "4.8"
  },
  {
    "rank": 89,
    "title": "2 Pack Wireless Lavalier Microphone for iPhone iPad and Android Phone, Lapel Mic Plug and Play Wireless Mic Noise Reduction Mini Microphone for Video Recording Interview Podcast Vlog YouTube Tiktok",
    "link": "https://www.amazon.com/KUKIHO-Microphone-Mic-Reduction-Recording/dp/B0DDCHN5WW/ref=zg_bs_g_musical-instruments_d_sccl_30/131-9998848-2129151?psc=1?tag=101e2e-20",
    "image": "https://images-na.ssl-images-amazon.com/images/I/71BeToboAFL._AC_UL300_SR300,200_.jpg",
    "price": "$13.29",
    "rating": "4.3"
  }
]